cdk/__init__.py
cdk/py.typed
cdk/_jsii/__init__.py
cdk/_jsii/zeroscaler-cdk@0.1.5.jsii.tgz
zeroscaler-0.1.5.dist-info/LICENSE
zeroscaler-0.1.5.dist-info/METADATA
zeroscaler-0.1.5.dist-info/WHEEL
zeroscaler-0.1.5.dist-info/top_level.txt
zeroscaler-0.1.5.dist-info/RECORD
